[
  {
    "title": "General",
    "subchapters": [
      {
        "title": "Overview",
        "subchapters": [],
        "optional": false,
        "content": "",
        "found": false
      },
      {
        "title": "Security Levels",
        "subchapters": [],
        "optional": false,
        "content": "",
        "found": false
      },
      {
        "title": "Additional Information",
        "subchapters": [],
        "optional": true,
        "content": "",
        "found": false
      }
    ],
    "optional": false,
    "content": "",
    "found": false
  },
  {
    "title": "Cryptographic Module Specification",
    "subchapters": [
      {
        "title": "Description",
        "subchapters": [],
        "optional": false,
        "content": "",
        "found": false
      },
      {
        "title": "Tested and vendor affirmed module version and identification",
        "subchapters": [],
        "optional": false,
        "content": "",
        "found": false
      },
      {
        "title": "Excluded components",
        "subchapters": [],
        "optional": false,
        "content": "",
        "found": false
      },
      {
        "title": "Modes of operation",
        "subchapters": [],
        "optional": false,
        "content": "",
        "found": false
      },
      {
        "title": "Algorithms",
        "subchapters": [],
        "optional": false,
        "content": "",
        "found": false
      },
      {
        "title": "Security Function Implementations",
        "subchapters": [],
        "optional": false,
        "content": "",
        "found": false
      },
      {
        "title": "Algorithm Specific Information",
        "subchapters": [],
        "optional": false,
        "content": "",
        "found": false
      },
      {
        "title": "RBG and Entropy",
        "subchapters": [],
        "optional": false,
        "content": "",
        "found": false
      },
      {
        "title": "Key Generation",
        "subchapters": [],
        "optional": false,
        "content": "",
        "found": false
      },
      {
        "title": "Key Establishment",
        "subchapters": [],
        "optional": false,
        "content": "",
        "found": false
      },
      {
        "title": "Industry protocols",
        "subchapters": [],
        "optional": false,
        "content": "",
        "found": false
      },
      {
        "title": "Additional Information",
        "subchapters": [],
        "optional": true,
        "content": "",
        "found": false
      }
    ],
    "optional": false,
    "content": "",
    "found": false
  },
  {
    "title": "Cryptographic Module Interfaces",
    "subchapters": [
      {
        "title": "Ports and interfaces",
        "subchapters": [],
        "optional": false,
        "content": "",
        "found": false
      },
      {
        "title": "Trusted Channel Specification",
        "subchapters": [],
        "optional": true,
        "content": "",
        "found": false
      },
      {
        "title": "Control Interface Not Inhibited",
        "subchapters": [],
        "optional": true,
        "content": "",
        "found": false
      },
      {
        "title": "Additional Information",
        "subchapters": [],
        "optional": true,
        "content": "",
        "found": false
      }
    ],
    "optional": false,
    "content": "",
    "found": false
  },
  {
    "title": "Roles, Services, and Authentication",
    "subchapters": [
      {
        "title": "Authentication methods",
        "subchapters": [],
        "optional": false,
        "content": "",
        "found": false
      },
      {
        "title": "Roles",
        "subchapters": [],
        "optional": false,
        "content": "",
        "found": false
      },
      {
        "title": "Approved Services",
        "subchapters": [],
        "optional": false,
        "content": "",
        "found": false
      },
      {
        "title": "Non-Approved Services",
        "subchapters": [],
        "optional": false,
        "content": "",
        "found": false
      },
      {
        "title": "External Software/Firmware Loaded",
        "subchapters": [],
        "optional": false,
        "content": "",
        "found": false
      },
      {
        "title": "Bypass Actions and Status",
        "subchapters": [],
        "optional": true,
        "content": "",
        "found": false
      },
      {
        "title": "Cryptographic Output Actions and Status",
        "subchapters": [],
        "optional": true,
        "content": "",
        "found": false
      },
      {
        "title": "Additional Information",
        "subchapters": [],
        "optional": true,
        "content": "",
        "found": false
      }
    ],
    "optional": false,
    "content": "",
    "found": false
  },
  {
    "title": "Software/Firmware Security",
    "subchapters": [
      {
        "title": "Integrity Techniques",
        "subchapters": [],
        "optional": false,
        "content": "",
        "found": false
      },
      {
        "title": "Initiate on Demand",
        "subchapters": [],
        "optional": false,
        "content": "",
        "found": false
      },
      {
        "title": "Open-Source Parameters",
        "subchapters": [],
        "optional": true,
        "content": "",
        "found": false
      },
      {
        "title": "Additional Information",
        "subchapters": [],
        "optional": true,
        "content": "",
        "found": false
      }
    ],
    "optional": false,
    "content": "",
    "found": false
  },
  {
    "title": "Operational Environment",
    "subchapters": [
      {
        "title": "Operational Environment Type and Requirements",
        "subchapters": [],
        "optional": false,
        "content": "",
        "found": false
      },
      {
        "title": "Configuration Settings and Restriction",
        "subchapters": [],
        "optional": true,
        "content": "",
        "found": false
      },
      {
        "title": "Additional Information",
        "subchapters": [],
        "optional": true,
        "content": "",
        "found": false
      }
    ],
    "optional": false,
    "content": "",
    "found": false
  },
  {
    "title": "Physical Security",
    "subchapters": [
      {
        "title": "Mechanisms and Actions Required",
        "subchapters": [],
        "optional": true,
        "content": "",
        "found": false
      },
      {
        "title": "User Placed Tamper Seals",
        "subchapters": [],
        "optional": true,
        "content": "",
        "found": false
      },
      {
        "title": "Filler Panels",
        "subchapters": [],
        "optional": true,
        "content": "",
        "found": false
      },
      {
        "title": "Fault Induction Mitigation",
        "subchapters": [],
        "optional": true,
        "content": "",
        "found": false
      },
      {
        "title": "EFP/EFT Information",
        "subchapters": [],
        "optional": true,
        "content": "",
        "found": false
      },
      {
        "title": "Hardness Testing Temperature Ranges",
        "subchapters": [],
        "optional": true,
        "content": "",
        "found": false
      },
      {
        "title": "Additional Information",
        "subchapters": [],
        "optional": true,
        "content": "",
        "found": false
      }
    ],
    "optional": false,
    "content": "",
    "found": false
  },
  {
    "title": "Non-Invasive Security",
    "subchapters": [
      {
        "title": "Mitigation Techniques",
        "subchapters": [],
        "optional": true,
        "content": "",
        "found": false
      },
      {
        "title": "Effectiveness",
        "subchapters": [],
        "optional": true,
        "content": "",
        "found": false
      },
      {
        "title": "Additional Information",
        "subchapters": [],
        "optional": true,
        "content": "",
        "found": false
      }
    ],
    "optional": false,
    "content": "",
    "found": false
  },
  {
    "title": "Sensitive security parameters management",
    "subchapters": [
      {
        "title": "Storage Areas",
        "subchapters": [],
        "optional": false,
        "content": "",
        "found": false
      },
      {
        "title": "SSP Input-Output Methods",
        "subchapters": [],
        "optional": false,
        "content": "",
        "found": false
      },
      {
        "title": "SSP Zeroization Methods",
        "subchapters": [],
        "optional": false,
        "content": "",
        "found": false
      },
      {
        "title": "SSPs",
        "subchapters": [],
        "optional": false,
        "content": "",
        "found": false
      },
      {
        "title": "Transitions",
        "subchapters": [],
        "optional": true,
        "content": "",
        "found": false
      },
      {
        "title": "Additional Information",
        "subchapters": [],
        "optional": true,
        "content": "",
        "found": false
      }
    ],
    "optional": false,
    "content": "",
    "found": false
  },
  {
    "title": "Self-Tests",
    "subchapters": [
      {
        "title": "Pre-Operational Self-Tests",
        "subchapters": [],
        "optional": false,
        "content": "",
        "found": false
      },
      {
        "title": "Conditional Self-Tests",
        "subchapters": [],
        "optional": false,
        "content": "",
        "found": false
      },
      {
        "title": "Periodic Self-Test Information",
        "subchapters": [],
        "optional": false,
        "content": "",
        "found": false
      },
      {
        "title": "Error States",
        "subchapters": [],
        "optional": false,
        "content": "",
        "found": false
      },
      {
        "title": "Operator Initiation of Self-Tests",
        "subchapters": [],
        "optional": true,
        "content": "",
        "found": false
      },
      {
        "title": "Additional Information",
        "subchapters": [],
        "optional": true,
        "content": "",
        "found": false
      }
    ],
    "optional": false,
    "content": "",
    "found": false
  },
  {
    "title": "Life-Cycle assurance",
    "subchapters": [
      {
        "title": "Installation, Initialization, and Startup Procedures",
        "subchapters": [],
        "optional": false,
        "content": "",
        "found": false
      },
      {
        "title": "Administrator Guidance",
        "subchapters": [],
        "optional": false,
        "content": "",
        "found": false
      },
      {
        "title": "Non-Administrator Guidance",
        "subchapters": [],
        "optional": false,
        "content": "",
        "found": false
      },
      {
        "title": "Design and Rules",
        "subchapters": [],
        "optional": true,
        "content": "",
        "found": false
      },
      {
        "title": "Maintenance Requirements",
        "subchapters": [],
        "optional": true,
        "content": "",
        "found": false
      },
      {
        "title": "End of Life",
        "subchapters": [],
        "optional": true,
        "content": "",
        "found": false
      },
      {
        "title": "Additional Information",
        "subchapters": [],
        "optional": true,
        "content": "",
        "found": false
      }
    ],
    "optional": false,
    "content": "",
    "found": false
  },
  {
    "title": "Mitigation of other attacks",
    "subchapters": [
      {
        "title": "Attack List",
        "subchapters": [],
        "optional": true,
        "content": "",
        "found": false
      },
      {
        "title": "Mitigation Effectiveness",
        "subchapters": [],
        "optional": true,
        "content": "",
        "found": false
      },
      {
        "title": "Guidance and Constraints",
        "subchapters": [],
        "optional": true,
        "content": "",
        "found": false
      },
      {
        "title": "Additional Information",
        "subchapters": [],
        "optional": true,
        "content": "",
        "found": false
      }
    ],
    "optional": false,
    "content": "",
    "found": false
  }
]